adafair/__init__.py
adafair/AdaFair.py
adafair/AdaFairEQOP.py
adafair/AdaFairSP.py
adafair/load_adult.py
adafair-0.1.5.dist-info/LICENSE
adafair-0.1.5.dist-info/METADATA
adafair-0.1.5.dist-info/WHEEL
adafair-0.1.5.dist-info/RECORD
