Metadata-Version: 2.1
Name: adafair
Version: 0.1.5
Summary: Fairness-aware adaptive boosting classifier. See paper: "AdaFair: Cumulative Fairness Adaptive Boosting"
License: MIT
Author: Dr. Vasileios Iosifidis
Author-email: billiosifidis@gmail.com
Requires-Python: >=3.8,<4.0
Classifier: License :: OSI Approved :: MIT License
Classifier: Programming Language :: Python :: 3
Classifier: Programming Language :: Python :: 3.8
Classifier: Programming Language :: Python :: 3.9
Classifier: Programming Language :: Python :: 3.10
Classifier: Programming Language :: Python :: 3.11
Classifier: Programming Language :: Python :: 3.12
Requires-Dist: numpy (>=1.24.4,<2.0.0)
Requires-Dist: scikit-learn (>=1.3.2,<2.0.0)
Requires-Dist: scipy (>=1.9.3,<2.0.0)
Requires-Dist: threadpoolctl (>=3.2.0,<4.0.0)
